LICENSE
MANIFEST.in
README.txt
setup.py
django_luhublog.egg-info/PKG-INFO
django_luhublog.egg-info/SOURCES.txt
django_luhublog.egg-info/dependency_links.txt
django_luhublog.egg-info/pbr.json
django_luhublog.egg-info/requires.txt
django_luhublog.egg-info/top_level.txt
luhublog/__init__.py
luhublog/__init__.pyc
luhublog/admin.py
luhublog/admin.pyc
luhublog/app_settings.py
luhublog/app_settings.pyc
luhublog/apps.py
luhublog/apps.pyc
luhublog/context_processors.py
luhublog/context_processors.pyc
luhublog/feed.py
luhublog/feed.pyc
luhublog/forms.py
luhublog/forms.pyc
luhublog/managers.py
luhublog/managers.pyc
luhublog/settings.pyc
luhublog/urls.py
luhublog/urls.pyc
luhublog/views.py
luhublog/views.pyc
luhublog/migrations/0001_initial.py
luhublog/migrations/0001_initial.pyc
luhublog/migrations/0002_auto_20151022_1637.py
luhublog/migrations/0002_auto_20151022_1637.pyc
luhublog/migrations/__init__.py
luhublog/migrations/__init__.pyc
luhublog/models/__init__.py
luhublog/models/__init__.pyc
luhublog/models/author.py
luhublog/models/author.pyc
luhublog/models/blog.py
luhublog/models/blog.pyc
luhublog/models/entry.py
luhublog/models/entry.pyc
luhublog/models/seo.py
luhublog/models/seo.pyc
luhublog/templates/luhublog/__open_graph_tags.html
luhublog/templates/luhublog/__seo_entry_meta.html
luhublog/templates/luhublog/__twitter_card.html
luhublog/templates/luhublog/base.html
luhublog/templates/luhublog/entry_detail.html
luhublog/templates/luhublog/entry_list.html
luhublog/templatetags/__init__.py
luhublog/templatetags/__init__.pyc
luhublog/templatetags/blog_opengraph_tags.py
luhublog/templatetags/blog_opengraph_tags.pyc
luhublog/templatetags/blog_seo_tags.pyc
luhublog/templatetags/blog_twittercard_tags.py
luhublog/templatetags/blog_twittercard_tags.pyc
luhublog/templatetags/entry_tags.py
luhublog/templatetags/entry_tags.pyc
luhublog/templatetags/twittercard_tags.pyc